Milestone 3/rptr_handler.v
// module for read pointer handler 

module rptr_handler #(parameter PTR_WIDTH=3) (
  input rclk, rrst_n, r_en,
  input [PTR_WIDTH:0] g_wptr_sync,
  output reg [PTR_WIDTH:0] b_rptr, g_rptr,
  output reg empty
);

    wire [PTR_WIDTH:0] b_rptr_next;
    wire [PTR_WIDTH:0] g_rptr_next;
    wire rempty;

    assign b_rptr_next = b_rptr+(r_en & !empty);
    assign g_rptr_next = (b_rptr_next >>1)^b_rptr_next;
    assign rempty = (g_wptr_sync == g_rptr_next);
    
    always@(posedge rclk or negedge rrst_n) begin
        if(!rrst_n) begin
        b_rptr <= 0;
        g_rptr <= 0;
        end
        else begin
        b_rptr <= b_rptr_next;
        g_rptr <= g_rptr_next;
        end
    end
    
    always@(posedge rclk or negedge rrst_n) begin
        if(!rrst_n) empty <= 1;
        else        empty <= rempty;
    end
endmodule

Milestone 2/tb_rptr_handler.v
`timescale 1ns/1ps

module rptr_handler_tb;

  parameter PTR_WIDTH = 3;
  reg rclk, rrst_n, r_en;
  reg [PTR_WIDTH:0] g_wptr_sync;
  wire [PTR_WIDTH:0] b_rptr, g_rptr;
  wire empty;

  rptr_handler #(PTR_WIDTH) uut (
    .rclk(rclk),
    .rrst_n(rrst_n),
    .r_en(r_en),
    .g_wptr_sync(g_wptr_sync),
    .b_rptr(b_rptr),
    .g_rptr(g_rptr),
    .empty(empty)
  );

  always #5 rclk = ~rclk; // 100 MHz clock

  initial begin
    rclk = 0;
    rrst_n = 0;
    r_en = 0;
    g_wptr_sync = 0;

    $dumpfile("./outputs/rptr_handler.vcd");
    $dumpvars(0,rptr_handler_tb);

    #10;
    rrst_n = 1;

    // Setting g_wptr_sync ahead of g_rptr to simulate available data
    #10 g_wptr_sync = 1; 
    #10 r_en = 1;        
    #10 r_en = 0;

    #10 g_wptr_sync = 2; 
    #10 r_en = 1;
    #10 r_en = 0;

    #10 g_wptr_sync = 3;
    #10 r_en = 1;
    #10 r_en = 0;

    #20 r_en = 0;

    #50;

    $finish;
  end

endmodule

Milestone 2/outputs/rptr_handler.vcd
$date
	Thu Jul 03 22:36:48 2025
$end
$version
	Icarus Verilog
$end
$timescale
	1ps
$end
$scope module rptr_handler_tb $end
$var wire 4 ! g_rptr [3:0] $end
$var wire 1 " empty $end
$var wire 4 # b_rptr [3:0] $end
$var parameter 32 $ PTR_WIDTH $end
$var reg 4 % g_wptr_sync [3:0] $end
$var reg 1 & r_en $end
$var reg 1 ' rclk $end
$var reg 1 ( rrst_n $end
$scope module uut $end
$var wire 4 ) g_rptr_next [3:0] $end
$var wire 4 * g_wptr_sync [3:0] $end
$var wire 1 & r_en $end
$var wire 1 ' rclk $end
$var wire 1 ( rrst_n $end
$var wire 1 + rempty $end
$var wire 4 , b_rptr_next [3:0] $end
$var parameter 32 - PTR_WIDTH $end
$var reg 4 . b_rptr [3:0] $end
$var reg 1 " empty $end
$var reg 4 / g_rptr [3:0] $end
$upscope $end
$upscope $end
$enddefinitions $end
$comment Show the parameter values. $end
$dumpall
b11 -
b11 $
$end
#0
$dumpvars
b0 /
b0 .
b0 ,
1+
b0 *
b0 )
0(
0'
0&
b0 %
b0 #
1"
b0 !
$end
#5000
1'
#10000
0'
1(
#15000
1'
#20000
0'
0+
b1 %
b1 *
#25000
0"
1'
#30000
1+
b1 )
b1 ,
0'
1&
#35000
b1 !
b1 /
b1 ,
b1 #
b1 .
1"
1'
#40000
0'
0&
#45000
1'
#50000
0'
0+
b10 %
b10 *
#55000
0"
1'
#60000
0+
b11 )
b10 ,
0'
1&
#65000
1+
b10 )
b11 !
b11 /
b11 ,
b10 #
b10 .
1'
#70000
0+
b11 )
b10 ,
0'
0&
#75000
1'
#80000
0'
1+
b11 %
b11 *
#85000
1"
1'
#90000
0'
1&
#95000
1'
#100000
0'
0&
