Milestone 2/wptr_handler.v
// module for write pointer handler 

module wptr_handler #(parameter PTR_WIDTH=3) (
  input wclk, wrst_n, w_en,
  input [PTR_WIDTH:0] g_rptr_sync,
  output reg [PTR_WIDTH:0] b_wptr, g_wptr,
  output reg full
);

  wire [PTR_WIDTH:0] b_wptr_next;
  wire [PTR_WIDTH:0] g_wptr_next;
   
  reg wrap_around;
  wire wfull;
  
  assign b_wptr_next = b_wptr+(w_en & !full);
  assign g_wptr_next = (b_wptr_next >>1)^b_wptr_next; //converting binary to gray 
  
  always@(posedge wclk or negedge wrst_n) begin
    if(!wrst_n) begin
      b_wptr <= 0;
      g_wptr <= 0;
    end
    else begin
      b_wptr <= b_wptr_next; // increment binary write pointer
      g_wptr <= g_wptr_next; // increment gray write pointer
    end
  end
  
  always@(posedge wclk or negedge wrst_n) begin
    if(!wrst_n) full <= 0;
    else        full <= wfull;
  end

  assign wfull = (g_wptr_next == {~g_rptr_sync[PTR_WIDTH:PTR_WIDTH-1], g_rptr_sync[PTR_WIDTH-2:0]});

endmodule

Milestone 2/tb_wptr_handler.v
// Testbench for wptr_handler module

`timescale 1ns / 1ps

module tb_wptr_handler;

  parameter PTR_WIDTH = 3; 

  reg wclk;
  reg wrst_n;
  reg w_en;
  reg [PTR_WIDTH:0] g_rptr_sync;

  wire [PTR_WIDTH:0] b_wptr;
  wire [PTR_WIDTH:0] g_wptr;
  wire full;

  wptr_handler #(
    .PTR_WIDTH(PTR_WIDTH)
  ) uut (
    .wclk(wclk),
    .wrst_n(wrst_n),
    .w_en(w_en),
    .g_rptr_sync(g_rptr_sync),
    .b_wptr(b_wptr),
    .g_wptr(g_wptr),
    .full(full)
  );

  // Clock generation
  initial begin
    wclk = 0;
    forever #5 wclk = ~wclk; // 10ns period
  end

  initial begin
    wrst_n = 0; 
    w_en = 0;
    g_rptr_sync = 0;

    // Dump all signals in this scope to VCD file for GTKWave
    $dumpfile("./outputs/wptrhandler.vcd");
    $dumpvars(0, tb_wptr_handler); // Dumps all signals in the current scope (tb_wptr_handler)

    #10; // Wait for 10ns (2 clock cycles) for reset to be stable
    wrst_n = 1; // De-assert reset

    #40
    w_en = 1;
    
    #1000
    $finish;

  end
endmodule

Milestone 2/outputs/wptrhandler.vcd
$date
	Thu Jul 03 20:34:42 2025
$end
$version
	Icarus Verilog
$end
$timescale
	1ps
$end
$scope module tb_wptr_handler $end
$var wire 4 ! g_wptr [3:0] $end
$var wire 1 " full $end
$var wire 4 # b_wptr [3:0] $end
$var parameter 32 $ PTR_WIDTH $end
$var reg 4 % g_rptr_sync [3:0] $end
$var reg 1 & w_en $end
$var reg 1 ' wclk $end
$var reg 1 ( wrst_n $end
$scope module uut $end
$var wire 4 ) g_rptr_sync [3:0] $end
$var wire 4 * g_wptr_next [3:0] $end
$var wire 1 & w_en $end
$var wire 1 ' wclk $end
$var wire 1 ( wrst_n $end
$var wire 1 + wfull $end
$var wire 4 , b_wptr_next [3:0] $end
$var parameter 32 - PTR_WIDTH $end
$var reg 4 . b_wptr [3:0] $end
$var reg 1 " full $end
$var reg 4 / g_wptr [3:0] $end
$upscope $end
$upscope $end
$enddefinitions $end
$comment Show the parameter values. $end
$dumpall
b11 -
b11 $
$end
#0
$dumpvars
b0 /
b0 .
b0 ,
0+
b0 *
b0 )
0(
0'
0&
b0 %
b0 #
0"
b0 !
$end
#5000
1'
#10000
0'
1(
#15000
1'
#20000
0'
#25000
1'
#30000
0'
#35000
1'
#40000
0'
#45000
1'
#50000
b1 *
b1 ,
0'
1&
#55000
b11 *
b1 !
b1 /
b10 ,
b1 #
b1 .
1'
#60000
0'
#65000
b10 *
b11 !
b11 /
b11 ,
b10 #
b10 .
1'
#70000
0'
#75000
b110 *
b10 !
b10 /
b100 ,
b11 #
b11 .
1'
#80000
0'
#85000
b111 *
b110 !
b110 /
b101 ,
b100 #
b100 .
1'
#90000
0'
#95000
b101 *
b111 !
b111 /
b110 ,
b101 #
b101 .
1'
#100000
0'
#105000
b100 *
b101 !
b101 /
b111 ,
b110 #
b110 .
1'
#110000
0'
#115000
1+
b1100 *
b100 !
b100 /
b1000 ,
b111 #
b111 .
1'
#120000
0'
#125000
1+
b1100 *
1"
b1100 !
b1100 /
b1000 ,
b1000 #
b1000 .
1'
