Milestone 1/mem.v
module fifo_mem #(parameter DEPTH=8, DATA_WIDTH=8, PTR_WIDTH=3) (
  input wclk, w_en, rclk, r_en,
  input [PTR_WIDTH:0] b_wptr, b_rptr,
  input [DATA_WIDTH-1:0] data_in,
  input full, empty,
  output reg [DATA_WIDTH-1:0] data_out);

  reg [DATA_WIDTH-1:0] fifo[0:DEPTH-1];

  always@(posedge wclk) begin
    if(w_en & !full) begin
      fifo[b_wptr[PTR_WIDTH-1:0]] <= data_in;
    end
  end

  always@(posedge rclk) begin
    if(r_en & !empty) begin
      data_out <= fifo[b_rptr[PTR_WIDTH-1:0]];
    end
  end

endmodule

Milestone 1/mem_tb.v
`timescale 1ns / 1ps 

module tb_fifo_mem;
  parameter DEPTH      = 8;
  parameter DATA_WIDTH = 8;
  parameter PTR_WIDTH  = 3; 

  reg wclk;           
  reg w_en;           
  reg rclk;            
  reg r_en;           
  reg [PTR_WIDTH:0] b_wptr;  
  reg [PTR_WIDTH:0] b_rptr;  
  reg [DATA_WIDTH-1:0] data_in; 
  reg full;            
  reg empty;           
  wire [DATA_WIDTH-1:0] data_out; 

  parameter WCLK_PERIOD = 10; // Write clock period (100 MHz)
  parameter RCLK_PERIOD = 15; // Read clock period (~66.6 MHz)

  always #((WCLK_PERIOD)/2) wclk = ~wclk; 
  always #((RCLK_PERIOD)/2) rclk = ~rclk; 

  // Internal counters to simulate FIFO pointer logic and full/empty for the test
  reg [PTR_WIDTH:0] tb_wptr_counter;
  reg [PTR_WIDTH:0] tb_rptr_counter;
  reg [PTR_WIDTH:0] fifo_level; 

  fifo_mem #(
    .DEPTH(DEPTH),
    .DATA_WIDTH(DATA_WIDTH),
    .PTR_WIDTH(PTR_WIDTH)
  ) fifo_mem (
    .wclk(wclk),
    .w_en(w_en),
    .rclk(rclk),
    .r_en(r_en),
    .b_wptr(b_wptr),
    .b_rptr(b_rptr),
    .data_in(data_in),
    .full(full),
    .empty(empty),
    .data_out(data_out)
  );

  initial begin
    wclk = 0;
    rclk = 0;
    w_en = 0;
    r_en = 0;
    data_in = 0;
    full = 0;
    empty = 1; 
    b_wptr = 0;
    b_rptr = 0;
    tb_wptr_counter = 0;
    tb_rptr_counter = 0;
    fifo_level = 0;

    $dumpfile("fifo_mem_tb.vcd");
    $dumpvars(0, tb_fifo_mem);

    $display("[%0t] Initializing signals...", $time);
    #50; 

    // Perform Writes
    $display("[%0t] --- Starting Write Operations ---", $time);
    w_en = 1; 
    empty = 0; 

    // Write 5 data items
    repeat (5) begin
      @(posedge wclk); 
      if (!full) begin
        data_in = $urandom_range(255, 0); // random data 
        b_wptr = tb_wptr_counter; // Assign current write pointer to DUT input
        $display("[%0t] Write: d_in = %h, b_wptr = %d, fifo_level = %d", $time, data_in, b_wptr, fifo_level);
        tb_wptr_counter = (tb_wptr_counter + 1) % DEPTH; 
        fifo_level = fifo_level + 1; 
        if (fifo_level == DEPTH) full = 1; 
      end else begin
        $display("[%0t] FIFO Full, skipping write.", $time);
      end
    end

    w_en = 0; 
    $display("[%0t] --- Write Operations Finished ---", $time);
    #WCLK_PERIOD; 

    //Perform Reads
    $display("[%0t] --- Starting Read Operations ---", $time);
    r_en = 1; 
    full = 0; 

    // Read 3 data items
    repeat (3) begin
      @(posedge rclk); 
      if (!empty) begin
        b_rptr = tb_rptr_counter; // Assign current read pointer to DUT input
        $display("[%0t] Read: d_out = %h, b_rptr = %d, fifo_level = %d", $time, data_out, b_rptr, fifo_level);
        tb_rptr_counter = (tb_rptr_counter + 1) % DEPTH; 
        fifo_level = fifo_level - 1; 
        if (fifo_level == 0) empty = 1; 
      end else begin
        $display("[%0t] FIFO Empty, skipping read.", $time);
      end
    end

    r_en = 0; 
    $display("[%0t] --- Read Operations Finished ---", $time);
    #RCLK_PERIOD; 

    // Mix Writes and Reads
    $display("[%0t] --- Mixing Write and Read Operations ---", $time);
    // Write 2 more items
    w_en = 1;
    empty = 0;
    repeat (2) begin
      @(posedge wclk);
      if (!full) begin
        data_in = $urandom_range(255, 0);
        b_wptr = tb_wptr_counter;
        $display("[%0t] Mixed Write: d_in = %h, b_wptr = %d, fifo_level = %d", $time, data_in, b_wptr, fifo_level);
        tb_wptr_counter = (tb_wptr_counter + 1) % DEPTH;
        fifo_level = fifo_level + 1;
        if (fifo_level == DEPTH) full = 1;
      end
    end
    w_en = 0;

    // Read 4 items 
    r_en = 1;
    full = 0;
    repeat (4) begin
      @(posedge rclk);
      if (!empty) begin
        b_rptr = tb_rptr_counter;
        $display("[%0t] Mixed Read: d_out = %h, b_rptr = %d, fifo_level = %d", $time, data_out, b_rptr, fifo_level);
        tb_rptr_counter = (tb_rptr_counter + 1) % DEPTH;
        fifo_level = fifo_level - 1;
        if (fifo_level == 0) empty = 1;
      end
    end
    r_en = 0;

    #((WCLK_PERIOD + RCLK_PERIOD) * 2); 

    $display("[%0t] --- Testbench Finished ---", $time);
    $finish; 
  end

endmodule

Milestone 1/fifo_mem_tb.vcd
$date
	Mon Jun 16 23:39:30 2025
$end
$version
	Icarus Verilog
$end
$timescale
	1ps
$end
$scope module tb_fifo_mem $end
$var wire 8 ! data_out [7:0] $end
$var parameter 32 " DATA_WIDTH $end
$var parameter 32 # DEPTH $end
$var parameter 32 $ PTR_WIDTH $end
$var parameter 32 % RCLK_PERIOD $end
$var parameter 32 & WCLK_PERIOD $end
$var reg 4 ' b_rptr [3:0] $end
$var reg 4 ( b_wptr [3:0] $end
$var reg 8 ) data_in [7:0] $end
$var reg 1 * empty $end
$var reg 4 + fifo_level [3:0] $end
$var reg 1 , full $end
$var reg 1 - r_en $end
$var reg 1 . rclk $end
$var reg 4 / tb_rptr_counter [3:0] $end
$var reg 4 0 tb_wptr_counter [3:0] $end
$var reg 1 1 w_en $end
$var reg 1 2 wclk $end
$scope module fifo_mem $end
$var wire 4 3 b_rptr [3:0] $end
$var wire 4 4 b_wptr [3:0] $end
$var wire 8 5 data_in [7:0] $end
$var wire 1 * empty $end
$var wire 1 , full $end
$var wire 1 - r_en $end
$var wire 1 . rclk $end
$var wire 1 1 w_en $end
$var wire 1 2 wclk $end
$var parameter 32 6 DATA_WIDTH $end
$var parameter 32 7 DEPTH $end
$var parameter 32 8 PTR_WIDTH $end
$var reg 8 9 data_out [7:0] $end
$upscope $end
$upscope $end
$enddefinitions $end
$comment Show the parameter values. $end
$dumpall
b11 8
b1000 7
b1000 6
b1010 &
b1111 %
b11 $
b1000 #
b1000 "
$end
#0
$dumpvars
bx 9
b0 5
b0 4
b0 3
02
01
b0 0
b0 /
0.
0-
0,
b0 +
1*
b0 )
b0 (
b0 '
bx !
$end
#5000
12
#7000
1.
#10000
02
#14000
0.
#15000
12
#20000
02
#21000
1.
#25000
12
#28000
0.
#30000
02
#35000
12
1.
#40000
02
#42000
0.
#45000
12
#49000
1.
#50000
02
0*
11
#55000
b1 +
b1 0
b10010010 )
b10010010 5
12
#56000
0.
#60000
02
#63000
1.
#65000
b10 +
b10 0
b1 (
b1 4
b1000000 )
b1000000 5
12
#70000
02
0.
#75000
b11 +
b11 0
b10 (
b10 4
b100 )
b100 5
12
#77000
1.
#80000
02
#84000
0.
#85000
b100 +
b100 0
b11 (
b11 4
b110001 )
b110001 5
12
#90000
02
#91000
1.
#95000
01
b101 +
b101 0
b100 (
b100 4
b10000110 )
b10000110 5
12
#98000
0.
#100000
02
#105000
b10010010 !
b10010010 9
b100 +
b1 /
12
1.
1-
#110000
02
#112000
0.
#115000
12
#119000
b11 +
b10 /
b1 '
b1 3
1.
#120000
02
#125000
12
#126000
0.
#130000
02
#133000
0-
b10 +
b11 /
b10 '
b10 3
1.
#135000
12
#140000
02
0.
#145000
12
#147000
1.
#148000
11
#150000
02
#154000
0.
#155000
b11 +
b110 0
b101 (
b101 4
b11000110 )
b11000110 5
12
#160000
02
#161000
1.
#165000
1-
01
b100 +
b111 0
b110 (
b110 4
b110010 )
b110010 5
12
#168000
0.
#170000
02
#175000
bx !
bx 9
b11 +
b100 /
b11 '
b11 3
12
1.
#180000
02
#182000
0.
#185000
12
#189000
b10 +
b101 /
b100 '
b100 3
1.
#190000
02
#195000
12
#196000
0.
#200000
02
#203000
b11000110 !
b11000110 9
b1 +
b110 /
b101 '
b101 3
1.
#205000
12
#210000
02
0.
#215000
12
#217000
0-
1*
b0 +
b111 /
b110 '
b110 3
1.
