Milestone 1/twoff_sync.v
module synchronizer #(parameter WIDTH=3) (input clk, rst_n, input [WIDTH:0] d_in, output reg [WIDTH:0] d_out);
  reg [WIDTH:0] q1;
  always@(posedge clk) begin
    if(!rst_n) begin
      q1 <= 0;
      d_out <= 0;
    end
    else begin
      q1 <= d_in;
      d_out <= q1;
    end
  end
endmodule

Milestone 1/ff_sync_tb.v
// Testbench for the two flip-flop synchronizer module

`timescale 1ns / 1ps 

module tb_synchronizer;

  parameter WIDTH = 3; 

  reg clk;      
  reg rst_n;     
  reg [WIDTH:0] d_in;   
  wire [WIDTH:0] d_out;   

  parameter CLK_PERIOD = 10; // 10ns period, 100MHz clock
  always #((CLK_PERIOD)/2) clk = ~clk; 

  synchronizer #(
    .WIDTH(WIDTH) 
  ) ff_sync (
    .clk(clk),    
    .rst_n(rst_n),   
    .d_in(d_in),     
    .d_out(d_out)    
  );

  initial begin

    clk = 0;       
    rst_n = 0;    
    d_in = 0;      

    $dumpfile("synchronizer_tb.vcd"); 
    $dumpvars(0, tb_synchronizer);     

    // Apply reset and hold for a few clock cycles
    #(CLK_PERIOD * 2);

    //Release reset and observe initial state
    rst_n = 1;    
    #(CLK_PERIOD);  

    // Test case 1: Change d_in to a new value
    d_in = 4'hA; 
    #(CLK_PERIOD * 2); 

    // Test case 2: Change d_in to another value
    d_in = 4'h3; 
    #(CLK_PERIOD * 2); 

    // Test case 3: d_in changes mid-cycle
    d_in = 4'hF; 
    #((CLK_PERIOD / 2) + 1); // Change d_in just after posedge clk (asynchronous change)
    d_in = 4'h5;
    #(CLK_PERIOD * 2); 

    // Test case 4: d_in changes multiple times rapidly 
    d_in = 4'h1;
    #((CLK_PERIOD / 4));
    d_in = 4'h2;
    #((CLK_PERIOD / 4));
    d_in = 4'hE;
    #(CLK_PERIOD * 2);

    $finish; 
  end

endmodule

Milestone 1/synchronizer_tb.vcd
$date
	Mon Jun 16 23:49:50 2025
$end
$version
	Icarus Verilog
$end
$timescale
	1ps
$end
$scope module tb_synchronizer $end
$var wire 4 ! d_out [3:0] $end
$var parameter 32 " CLK_PERIOD $end
$var parameter 32 # WIDTH $end
$var reg 1 $ clk $end
$var reg 4 % d_in [3:0] $end
$var reg 1 & rst_n $end
$scope module ff_sync $end
$var wire 1 $ clk $end
$var wire 4 ' d_in [3:0] $end
$var wire 1 & rst_n $end
$var parameter 32 ( WIDTH $end
$var reg 4 ) d_out [3:0] $end
$var reg 4 * q1 [3:0] $end
$upscope $end
$upscope $end
$enddefinitions $end
$comment Show the parameter values. $end
$dumpall
b11 (
b11 #
b1010 "
$end
#0
$dumpvars
bx *
bx )
b0 '
0&
b0 %
0$
bx !
$end
#5000
b0 !
b0 )
b0 *
1$
#10000
0$
#15000
1$
#20000
0$
1&
#25000
1$
#30000
0$
b1010 %
b1010 '
#35000
b1010 *
1$
#40000
0$
#45000
b1010 !
b1010 )
1$
#50000
0$
b11 %
b11 '
#55000
b11 *
1$
#60000
0$
#65000
b11 !
b11 )
1$
#70000
0$
b1111 %
b1111 '
#75000
b1111 *
1$
#76000
b101 %
b101 '
#80000
0$
#85000
b1111 !
b1111 )
b101 *
1$
#90000
0$
#95000
b101 !
b101 )
1$
#96000
b1 %
b1 '
#98000
b10 %
b10 '
#100000
b1110 %
b1110 '
0$
#105000
b1110 *
1$
#110000
0$
#115000
b1110 !
b1110 )
1$
